{"Araria":{"Blocks":"Bhargama"},"Arwal":{"Blocks":"Ratni Faridpur"},"Aurangabad":{"Blocks":"Haspura"},"Banka":{"Blocks":"Katoria"},"Begusarai":{"Blocks":"Mansoorchak"},"Bhagalpur":{"Blocks":"Rangrachowk"},"Bhojpur":{"Blocks":"Tarari"},"Buxar":{"Blocks":"Simri"},"Darbhanga":{"Blocks":"Gaura Bauram"},"East Champaran":{"Blocks":"Kalyanpur"},"Gaya":{"Blocks":"Paraiya"},"Gopalganj":{"Blocks":"Vijayipur"},"Jamui":{"Blocks":"Islamnagaraliganj"},"Jehanabad":{"Blocks":"Makhdumpur"},"Kaimur":{"Blocks":"Nuaon"},"Katihar":{"Blocks":"Amdabad"},"Khagaria":{"Blocks":"Parbatta"},"Kishanganj":{"Blocks":"Thakurganj"},"Lakhisarai":{"Blocks":"Pipariya"},"Madhepura":{"Blocks":"Alamnagar"},"Madhubani":{"Blocks":"Basopatti"},"Munger":{"Blocks":"Sangrampur"},"Muzaffarpur":{"Blocks":"Saraiya"},"Nalanda":{"Blocks":"Silao"},"Nawada":{"Blocks":"Siradala"},"Patna":{"Blocks":"Bikram"},"Purnia":{"Blocks":"Dagarua"},"Rohtas":{"Blocks":"Tilouthu"},"Saharsa":{"Blocks":"Banma Itahri"},"Samastipur":{"Blocks":"Mohiuddin Nagar"},"Saran":{"Blocks":"Sonepur"},"Sheikhpura":{"Blocks":"Shekhopur Sarai"},"Sheohar":{"Blocks":"Parsauni"},"Sitamarhi":{"Blocks":"Sursand"},"Siwan":{"Blocks":"Lakri Nabiganj"},"Supaul":{"Blocks":"Chhatapur"},"Vaishali":{"Blocks":"Sahdei Buzurg"},"West Champaran":{"Blocks":"Ramnagar"}}